neural_data_simulator/__init__.py
neural_data_simulator/config/lsl.config
neural_data_simulator/config/settings.yaml
neural_data_simulator/core/__init__.py
neural_data_simulator/core/encoder.py
neural_data_simulator/core/ephys_generator.py
neural_data_simulator/core/filters.py
neural_data_simulator/core/health_checker.py
neural_data_simulator/core/inputs/__init__.py
neural_data_simulator/core/inputs/api.py
neural_data_simulator/core/inputs/lsl_input.py
neural_data_simulator/core/inputs/samples_input.py
neural_data_simulator/core/inputs/testing_input.py
neural_data_simulator/core/models.py
neural_data_simulator/core/outputs/api.py
neural_data_simulator/core/outputs/lsl_output.py
neural_data_simulator/core/runner.py
neural_data_simulator/core/samples.py
neural_data_simulator/core/settings.py
neural_data_simulator/core/timing.py
neural_data_simulator/decoder/__init__.py
neural_data_simulator/decoder/config/settings_decoder.yaml
neural_data_simulator/decoder/decoders.py
neural_data_simulator/decoder/run_decoder.py
neural_data_simulator/decoder/settings.py
neural_data_simulator/plugins/__init__.py
neural_data_simulator/plugins/examples/custom_script.py
neural_data_simulator/plugins/examples/gamepad_preprocessor.py
neural_data_simulator/plugins/examples/model.py
neural_data_simulator/plugins/examples/postprocessor.py
neural_data_simulator/plugins/examples/preprocessor.py
neural_data_simulator/plugins/examples/tests/test_model.py
neural_data_simulator/recorder/__init__.py
neural_data_simulator/recorder/recorders.py
neural_data_simulator/recorder/run_recorder.py
neural_data_simulator/scripts/__init__.py
neural_data_simulator/scripts/errors.py
neural_data_simulator/scripts/post_install_config.py
neural_data_simulator/scripts/run_encoder.py
neural_data_simulator/scripts/run_ephys_generator.py
neural_data_simulator/streamer/__init__.py
neural_data_simulator/streamer/config/settings_streamer.yaml
neural_data_simulator/streamer/run_streamer.py
neural_data_simulator-0.2.10.dist-info/LICENSE
neural_data_simulator-0.2.10.dist-info/METADATA
neural_data_simulator-0.2.10.dist-info/WHEEL
neural_data_simulator-0.2.10.dist-info/entry_points.txt
neural_data_simulator-0.2.10.dist-info/RECORD
